QCustomPlot_PyQt6.cpython-314-x86_64-linux-gnu.so
qcustomplot_pyqt6-2.1.1.2.dist-info/WHEEL
qcustomplot_pyqt6-2.1.1.2.dist-info/METADATA
qcustomplot_pyqt6-2.1.1.2.dist-info/RECORD
