Metadata-Version: 2.2
Name: QCustomPlot_PyQt6
Version: 2.1.1.2
Requires-Python: >=3.7
Summary: QCustomPlot is a Qt widget for plotting and data visualization
Project-Url: homepage, https://github.com/salsergey/QCustomPlot-PyQt
License: MIT
Keywords: PyQt, QCustomPlot, GUI
Author: Sergey Salnikov
Author-Email: salsergey@gmail.com
Classifier: Development Status :: 5 - Production/Stable
Classifier: Environment :: X11 Applications :: Qt
Classifier: Intended Audience :: Developers
Classifier: License :: OSI Approved :: MIT License
Classifier: Operating System :: POSIX :: Linux
Classifier: Operating System :: Microsoft :: Windows
Classifier: Programming Language :: Python :: 3
Classifier: Programming Language :: Python :: 3.7
Classifier: Programming Language :: Python :: 3.8
Classifier: Programming Language :: Python :: 3.9
Classifier: Programming Language :: Python :: 3.10
Classifier: Programming Language :: Python :: 3.11
Classifier: Programming Language :: Python :: 3.12
Classifier: Topic :: Software Development :: User Interfaces
Requires-Dist: PyQt6-sip (>=13.8, <14)
Requires-Dist: PyQt6
